{"version":1,"sessions":{"553d2747-8f4b-4ed2-9013-5f0c7a4d100f":{"updatedAt":1782803773481,"files":{"C:\\Users\\kimgi\\Documents\\Life\\gihyun-portfolio\\next.config.ts":{"editCount":2,"findings":[]},"C:\\Users\\kimgi\\Documents\\Life\\gihyun-portfolio\\src\\app\\globals.css":{"editCount":10,"findings":["layout-transition:247","layout-transition:257","layout-transition:258","layout-transition:538"]},"C:\\Users\\kimgi\\Documents\\Life\\gihyun-portfolio\\src\\lib\\data\\profile.ts":{"editCount":1,"findings":[]},"C:\\Users\\kimgi\\Documents\\Life\\gihyun-portfolio\\src\\lib\\data\\cv.ts":{"editCount":1,"findings":[]},"C:\\Users\\kimgi\\Documents\\Life\\gihyun-portfolio\\src\\lib\\data\\projects.ts":{"editCount":1,"findings":[]},"C:\\Users\\kimgi\\Documents\\Life\\gihyun-portfolio\\src\\lib\\data\\travel.ts":{"editCount":1,"findings":[]},"C:\\Users\\kimgi\\Documents\\Life\\gihyun-portfolio\\src\\lib\\data\\offduty.ts":{"editCount":1,"findings":[]},"C:\\Users\\kimgi\\Documents\\Life\\gihyun-portfolio\\src\\lib\\posts.ts":{"editCount":1,"findings":[]},"C:\\Users\\kimgi\\Documents\\Life\\gihyun-portfolio\\src\\app\\layout.tsx":{"editCount":1,"findings":[]},"C:\\Users\\kimgi\\Documents\\Life\\gihyun-portfolio\\src\\lib\\theme.ts":{"editCount":1,"findings":[]},"C:\\Users\\kimgi\\Documents\\Life\\gihyun-portfolio\\src\\components\\providers\\SmoothScroll.tsx":{"editCount":1,"findings":[]},"C:\\Users\\kimgi\\Documents\\Life\\gihyun-portfolio\\src\\components\\chrome\\Cursor.tsx":{"editCount":1,"findings":[]},"C:\\Users\\kimgi\\Documents\\Life\\gihyun-portfolio\\src\\components\\ui\\Magnetic.tsx":{"editCount":1,"findings":[]},"C:\\Users\\kimgi\\Documents\\Life\\gihyun-portfolio\\src\\components\\ui\\Reveal.tsx":{"editCount":3,"findings":[]},"C:\\Users\\kimgi\\Documents\\Life\\gihyun-portfolio\\src\\components\\ui\\TextReveal.tsx":{"editCount":3,"findings":[]},"C:\\Users\\kimgi\\Documents\\Life\\gihyun-portfolio\\src\\components\\chrome\\ThemeToggle.tsx":{"editCount":1,"findings":[]},"C:\\Users\\kimgi\\Documents\\Life\\gihyun-portfolio\\src\\components\\chrome\\Nav.tsx":{"editCount":2,"findings":[]},"C:\\Users\\kimgi\\Documents\\Life\\gihyun-portfolio\\src\\components\\chrome\\Footer.tsx":{"editCount":1,"findings":[]},"C:\\Users\\kimgi\\Documents\\Life\\gihyun-portfolio\\src\\components\\chrome\\Preloader.tsx":{"editCount":1,"findings":[]},"C:\\Users\\kimgi\\Documents\\Life\\gihyun-portfolio\\src\\components\\three\\ModelViewer.tsx":{"editCount":4,"findings":[]},"C:\\Users\\kimgi\\Documents\\Life\\gihyun-portfolio\\src\\components\\three\\GyroidHero.tsx":{"editCount":2,"findings":[]},"C:\\Users\\kimgi\\Documents\\Life\\gihyun-portfolio\\src\\components\\three\\Globe.tsx":{"editCount":1,"findings":[]},"C:\\Users\\kimgi\\Documents\\Life\\gihyun-portfolio\\src\\components\\home\\HomeHero.tsx":{"editCount":1,"findings":[]},"C:\\Users\\kimgi\\Documents\\Life\\gihyun-portfolio\\src\\components\\ui\\Marquee.tsx":{"editCount":1,"findings":[]},"C:\\Users\\kimgi\\Documents\\Life\\gihyun-portfolio\\src\\components\\home\\WorkPreview.tsx":{"editCount":1,"findings":[]},"C:\\Users\\kimgi\\Documents\\Life\\gihyun-portfolio\\src\\app\\page.tsx":{"editCount":1,"findings":[]},"C:\\Users\\kimgi\\Documents\\Life\\gihyun-portfolio\\src\\components\\ui\\Gallery.tsx":{"editCount":1,"findings":[]},"C:\\Users\\kimgi\\Documents\\Life\\gihyun-portfolio\\src\\components\\portfolio\\ActiveViewer.tsx":{"editCount":1,"findings":[]},"C:\\Users\\kimgi\\Documents\\Life\\gihyun-portfolio\\src\\components\\portfolio\\PortfolioExplorer.tsx":{"editCount":1,"findings":[]},"C:\\Users\\kimgi\\Documents\\Life\\gihyun-portfolio\\src\\app\\portfolio\\page.tsx":{"editCount":1,"findings":[]},"C:\\Users\\kimgi\\Documents\\Life\\gihyun-portfolio\\src\\components\\ui\\PageHeader.tsx":{"editCount":1,"findings":[]},"C:\\Users\\kimgi\\Documents\\Life\\gihyun-portfolio\\src\\components\\cv\\CVTimeline.tsx":{"editCount":1,"findings":[]},"C:\\Users\\kimgi\\Documents\\Life\\gihyun-portfolio\\src\\app\\cv\\page.tsx":{"editCount":1,"findings":[]},"C:\\Users\\kimgi\\Documents\\Life\\gihyun-portfolio\\src\\app\\about\\page.tsx":{"editCount":1,"findings":[]},"C:\\Users\\kimgi\\Documents\\Life\\gihyun-portfolio\\src\\components\\personal\\JourneyGlobe.tsx":{"editCount":1,"findings":[]},"C:\\Users\\kimgi\\Documents\\Life\\gihyun-portfolio\\src\\components\\personal\\Keyboards.tsx":{"editCount":1,"findings":[]},"C:\\Users\\kimgi\\Documents\\Life\\gihyun-portfolio\\src\\app\\personal\\page.tsx":{"editCount":1,"findings":[]},"C:\\Users\\kimgi\\Documents\\Life\\gihyun-portfolio\\src\\app\\blog\\page.tsx":{"editCount":1,"findings":[]},"C:\\Users\\kimgi\\Documents\\Life\\gihyun-portfolio\\src\\components\\blog\\PostBody.tsx":{"editCount":2,"findings":[]},"C:\\Users\\kimgi\\Documents\\Life\\gihyun-portfolio\\src\\app\\blog\\[slug]\\page.tsx":{"editCount":1,"findings":[]},"C:\\Users\\kimgi\\Documents\\Life\\gihyunkim-com\\src\\lib\\data\\profile.ts":{"editCount":2,"findings":[]},"C:\\Users\\kimgi\\Documents\\Life\\gihyunkim-com\\src\\components\\home\\HomeHero.tsx":{"editCount":1,"findings":[]},"C:\\Users\\kimgi\\Documents\\Life\\gihyunkim-com\\src\\app\\globals.css":{"editCount":3,"findings":["side-tab:707","layout-transition:251","layout-transition:262"]},"C:\\Users\\kimgi\\Documents\\Life\\gihyunkim-com\\src\\components\\personal\\JourneyMap.tsx":{"editCount":1,"findings":[]},"C:\\Users\\kimgi\\Documents\\Life\\gihyunkim-com\\src\\app\\personal\\page.tsx":{"editCount":1,"findings":[]},"C:\\Users\\kimgi\\Documents\\Life\\gihyunkim-com\\src\\app\\about\\page.tsx":{"editCount":1,"findings":[]},"C:\\Users\\kimgi\\Documents\\Life\\gihyunkim-com\\src\\components\\chrome\\Nav.tsx":{"editCount":1,"findings":[]},"C:\\Users\\kimgi\\Documents\\Life\\gihyunkim-com\\src\\components\\chrome\\Preloader.tsx":{"editCount":1,"findings":[]},"C:\\Users\\kimgi\\Documents\\Life\\gihyunkim-com\\src\\app\\page.tsx":{"editCount":3,"findings":[]},"C:\\Users\\kimgi\\Documents\\Life\\gihyunkim-com\\src\\app\\portfolio\\page.tsx":{"editCount":2,"findings":[]},"C:\\Users\\kimgi\\Documents\\Life\\gihyunkim-com\\src\\lib\\data\\travel.ts":{"editCount":1,"findings":[]},"C:\\Users\\kimgi\\Documents\\Life\\gihyunkim-com\\src\\lib\\data\\offduty.ts":{"editCount":1,"findings":[]}}}}}